qoco/interface.py
qoco/__init__.py
qoco/qoco_ext.cpython-311-darwin.so
qoco-0.2.0.dist-info/RECORD
qoco-0.2.0.dist-info/WHEEL
qoco-0.2.0.dist-info/METADATA
qoco-0.2.0.dist-info/licenses/LICENSE
